[
    {
        "title": "本章重点",
        "analyze": []
    },
    {
        "title": "1==========",
        "analyze": null
    },
    {
        "title": "100、开展人员素质测评工作，首要任务就是要明确测评的目的。P329",
        "analyze": null
    },
    {
        "title": "101、人才选拔工作是企业人力资源管理的入口。P329",
        "analyze": null
    },
    {
        "title": "102、在测评内容的确定中，首先要确定的是测评要素，即从哪些角度衡量被测评者的特征。P335",
        "analyze": null
    },
    {
        "title": "103、测评指标是衡量和评价与工作有关的个人特征的维度，是对抽象的测评内容进行操作化的定义，是测评指标体系的基本单位。P346",
        "analyze": null
    },
    {
        "title": "2==========",
        "analyze": null
    },
    {
        "title": "3==========",
        "analyze": null
    },
    {
        "title": "30、测评的环境条件是影响被测评者测评成绩的重要因素，测评的环境包括【物理环境】和【心理环境】两个方面。P342",
        "analyze":null
    },
    {
        "title": "31、一般来说，经验丰富的测评者必须具备以下三个方面的资格能力：一是【理论知识】。二是【职业道德】。三是【专业水平】。P342",
        "analyze":null
    },
    {
        "title": "32、在实际测评中，误差分为【随机误差】和【系统误差】两种。P351",
        "analyze":null
    },
    {
        "title": "4==========",
        "analyze": null
    },
    {
        "title": "31、测评要素的设计模式有【个性理论模式、德能勤绩模式、陆氏模式和基于胜任特征的设计模式】等，现在最为常用的是基于胜任特征的设计模式。（或单）P335",
        "analyze": null
    },
    {
        "title": "32、信度和效度是衡量测评工具科学性的最重要的指标，一般来说，信度和效度越高的测评工具，科学性就越高。",
        "analyze": null
    },
    {
        "title": "33、一项完整的测评指标体系包括【测评要素、测评指标和评定标准】。（或单）P346",
        "analyze": null
    },
    {
        "title": "34、衡量测评方法的指标有四个，分别是【效度、公平度、可用性和成本】。P347",
        "analyze": null
    },
    {
        "title": "5==========",
        "analyze": null
    },
    {
        "title": "6==========",
        "analyze": null
    },
    {
        "title": "10、人员素质测评的实施流程。P333-341",
        "analyze": [
            "1）确定测评内容 ｜2）确定测评的基本形式和测评工具 ｜3）测评的实施与数据采集 ｜4）分析测评结果 ｜5）做出决策或建议 ｜6）跟踪检测和反馈"
        ]
    }
]